hybridfactory/__init__.py
hybridfactory/data/__init__.py
hybridfactory/data/annotation.py
hybridfactory/data/dataset.py
hybridfactory/generate/__init__.py
hybridfactory/generate/generator.py
hybridfactory/io/__init__.py
hybridfactory/io/spikegl.py
hybridfactory/probes/__init__.py
hybridfactory/probes/probe.py
hybridfactory/utils/__init__.py
hybridfactory/utils/cli.py
hybridfactory/utils/tools.py
hybridfactory/validate/__init__.py
hybridfactory/validate/comparison.py
hybridfactory/validate/visualize.py
hybridfactory-0.1.0b1.dist-info/LICENSE
hybridfactory-0.1.0b1.dist-info/METADATA
hybridfactory-0.1.0b1.dist-info/WHEEL
hybridfactory-0.1.0b1.dist-info/entry_points.txt
hybridfactory-0.1.0b1.dist-info/top_level.txt
hybridfactory-0.1.0b1.dist-info/RECORD
