Metadata-Version: 2.1
Name: hybridfactory
Version: 0.1.0b1
Summary: A utility for generating hybrid ephys data
Home-page: https://gitlab.com/vidriotech/spiegel/hybridfactory
Author: Alan Liddell
Author-email: alan@vidriotech.com
License: MIT
Platform: UNKNOWN
Classifier: Programming Language :: Python :: 3
Classifier: License :: OSI Approved :: MIT License
Classifier: Operating System :: OS Independent
